caretaker/__init__.py
caretaker/config.py
caretaker/ai/__init__.py
caretaker/ai/ai_playground.py
caretaker/ai/master.py
caretaker/ai/model.py
caretaker/decorators/__init__.py
caretaker/decorators/decorators.py
caretaker/prompts/__init__.py
caretaker/prompts/prompts.py
Caretaker-0.1.2.dist-info/LICENSE
Caretaker-0.1.2.dist-info/METADATA
Caretaker-0.1.2.dist-info/WHEEL
Caretaker-0.1.2.dist-info/top_level.txt
Caretaker-0.1.2.dist-info/RECORD
