Metadata-Version: 2.2
Name: Caretaker
Version: 0.1.2
Summary: Technology demonstrator self-adapting code
Home-page: https://github.com/greg-d128/caretaker
Author: Grzegorz Dostatni
Author-email: gregdostatni@gmail.com
Classifier: Programming Language :: Python :: 3
Classifier: License :: OSI Approved :: GNU General Public License v3 (GPLv3)
Classifier: Operating System :: OS Independent
Requires-Python: >=3.6
License-File: LICENSE
Dynamic: author
Dynamic: author-email
Dynamic: classifier
Dynamic: description
Dynamic: description-content-type
Dynamic: home-page
Dynamic: requires-python
Dynamic: summary
